tableau_sql_parser/__init__.py
tableau_sql_parser/cli.py
tableau_sql_parser/output_formatting.py
tableau_sql_parser/recursive_search.py
tableau_sql_parser/tableau_workbook.py
tableau_sql_parser/utils.py
tableau_sql_parser-0.2.2.dist-info/licenses/LICENSE
tableau_sql_parser-0.2.2.dist-info/METADATA
tableau_sql_parser-0.2.2.dist-info/WHEEL
tableau_sql_parser-0.2.2.dist-info/entry_points.txt
tableau_sql_parser-0.2.2.dist-info/top_level.txt
tableau_sql_parser-0.2.2.dist-info/RECORD
