Metadata-Version: 2.4
Name: tableau-sql-parser
Version: 0.2.2
Summary: A tool for parsing Tableau custom SQL queries and extracting useful information
Author-email: Florian Drouet <florian.drouet78@gmail.com>
License:                                  Apache License
Project-URL: Homepage, https://github.com/florian-drouet/tableau-sql-parser
Requires-Python: <3.11,>=3.9
License-File: LICENSE
Requires-Dist: lxml>=5.4.0
Requires-Dist: sqlfluff>=3.4.0
Dynamic: license-file
